sqlalchemy_continuum/__init__.py
sqlalchemy_continuum/builder.py
sqlalchemy_continuum/exc.py
sqlalchemy_continuum/expression_reflector.py
sqlalchemy_continuum/factory.py
sqlalchemy_continuum/fetcher.py
sqlalchemy_continuum/manager.py
sqlalchemy_continuum/model_builder.py
sqlalchemy_continuum/operation.py
sqlalchemy_continuum/relationship_builder.py
sqlalchemy_continuum/reverter.py
sqlalchemy_continuum/schema.py
sqlalchemy_continuum/table_builder.py
sqlalchemy_continuum/transaction.py
sqlalchemy_continuum/unit_of_work.py
sqlalchemy_continuum/utils.py
sqlalchemy_continuum/version.py
sqlalchemy_continuum/dialects/__init__.py
sqlalchemy_continuum/dialects/postgresql.py
sqlalchemy_continuum/plugins/__init__.py
sqlalchemy_continuum/plugins/activity.py
sqlalchemy_continuum/plugins/base.py
sqlalchemy_continuum/plugins/flask.py
sqlalchemy_continuum/plugins/null_delete.py
sqlalchemy_continuum/plugins/property_mod_tracker.py
sqlalchemy_continuum/plugins/transaction_changes.py
sqlalchemy_continuum/plugins/transaction_meta.py
SQLAlchemy_Continuum_Trialspark-1.5.0.dist-info/LICENSE
SQLAlchemy_Continuum_Trialspark-1.5.0.dist-info/METADATA
SQLAlchemy_Continuum_Trialspark-1.5.0.dist-info/WHEEL
SQLAlchemy_Continuum_Trialspark-1.5.0.dist-info/top_level.txt
SQLAlchemy_Continuum_Trialspark-1.5.0.dist-info/RECORD
