Metadata-Version: 2.1
Name: SQLAlchemy-Continuum-Trialspark
Version: 1.5.0
Summary: Versioning and auditing extension for SQLAlchemy.
Home-page: https://github.com/trialspark/sqlalchemy-continuum
Author: Konsta Vesterinen
Author-email: konsta@fastmonkeys.com
License: BSD
Platform: any
Classifier: Environment :: Web Environment
Classifier: Intended Audience :: Developers
Classifier: License :: OSI Approved :: BSD License
Classifier: Operating System :: OS Independent
Classifier: Programming Language :: Python
Classifier: Programming Language :: Python :: 2
Classifier: Programming Language :: Python :: 2.7
Classifier: Programming Language :: Python :: 3
Classifier: Programming Language :: Python :: 3.4
Classifier: Programming Language :: Python :: 3.5
Classifier: Programming Language :: Python :: 3.6
Classifier: Programming Language :: Python :: 3.7
Classifier: Topic :: Internet :: WWW/HTTP :: Dynamic Content
Classifier: Topic :: Software Development :: Libraries :: Python Modules
License-File: LICENSE
Requires-Dist: SQLAlchemy (>=1.0.8)
Requires-Dist: SQLAlchemy-Utils (>=0.30.12)
Provides-Extra: flask
Requires-Dist: Flask (>=0.9) ; extra == 'flask'
Provides-Extra: flask-login
Requires-Dist: Flask-Login (>=0.2.9) ; extra == 'flask-login'
Provides-Extra: flask-sqlalchemy
Requires-Dist: Flask-SQLAlchemy (>=1.0) ; extra == 'flask-sqlalchemy'
Provides-Extra: flexmock
Requires-Dist: flexmock (>=0.9.7) ; extra == 'flexmock'
Provides-Extra: i18n
Requires-Dist: SQLAlchemy-i18n (!=1.1.0,>=0.8.4) ; extra == 'i18n'
Provides-Extra: test
Requires-Dist: pytest (>=2.3.5) ; extra == 'test'
Requires-Dist: flexmock (>=0.9.7) ; extra == 'test'
Requires-Dist: psycopg2 (>=2.4.6) ; extra == 'test'
Requires-Dist: PyMySQL (>=0.8.0) ; extra == 'test'
Requires-Dist: six (>=1.4.0) ; extra == 'test'
Requires-Dist: Flask (>=0.9) ; extra == 'test'
Requires-Dist: Flask-Login (>=0.2.9) ; extra == 'test'
Requires-Dist: Flask-SQLAlchemy (>=1.0) ; extra == 'test'
Requires-Dist: SQLAlchemy-i18n (!=1.1.0,>=0.8.4) ; extra == 'test'
